platemap/__init__.py
platemap/plate.py
platemap/PlateUtils/__init__.py
platemap/PlateUtils/add_volume.py
platemap/PlateUtils/assign_source_wells.py
platemap/PlateUtils/find_next_well.py
platemap/PlateUtils/remove_volume.py
platemap/PlateUtils/transfer.py
platemap-0.0.10.dist-info/LICENSE.txt
platemap-0.0.10.dist-info/METADATA
platemap-0.0.10.dist-info/WHEEL
platemap-0.0.10.dist-info/top_level.txt
platemap-0.0.10.dist-info/RECORD
